floorer/__init__.py
floorer/floorer.py
floorer-0.1.6.dist-info/LICENSE
floorer-0.1.6.dist-info/METADATA
floorer-0.1.6.dist-info/WHEEL
floorer-0.1.6.dist-info/top_level.txt
floorer-0.1.6.dist-info/RECORD
