Metadata-Version: 2.1
Name: floorer
Version: 0.1.6
Summary: A small library to manage pandas DataFrames in Parquet files using PyArrow.
Home-page: https://github.com/rvabrilot/floorer
Author: Rodrigo Vera
Author-email: rvabrilot@gmail.com
License: UNKNOWN
Platform: UNKNOWN
Classifier: Programming Language :: Python :: 3
Classifier: License :: OSI Approved :: MIT License
Classifier: Operating System :: OS Independent
Requires-Python: >=3.6
License-File: LICENSE
Requires-Dist: pandas
Requires-Dist: pyarrow
